jobfunnel/__init__.py
jobfunnel/__main__.py
jobfunnel/backend/__init__.py
jobfunnel/backend/job.py
jobfunnel/backend/jobfunnel.py
jobfunnel/backend/scrapers/__init__.py
jobfunnel/backend/scrapers/base.py
jobfunnel/backend/scrapers/glassdoor.py
jobfunnel/backend/scrapers/indeed.py
jobfunnel/backend/scrapers/monster.py
jobfunnel/backend/scrapers/registry.py
jobfunnel/backend/tools/__init__.py
jobfunnel/backend/tools/delay.py
jobfunnel/backend/tools/filters.py
jobfunnel/backend/tools/tools.py
jobfunnel/config/__init__.py
jobfunnel/config/base.py
jobfunnel/config/cli.py
jobfunnel/config/delay.py
jobfunnel/config/manager.py
jobfunnel/config/proxy.py
jobfunnel/config/search.py
jobfunnel/config/settings.py
jobfunnel/resources/__init__.py
jobfunnel/resources/defaults.py
jobfunnel/resources/enums.py
jobfunnel/resources/resources.py
jobfunnel/resources/user_agent_list.txt
tests/backend/__init__.py
tests/backend/scrapers/__init__.py
tests/backend/scrapers/test_glassdoor.py
tests/backend/scrapers/test_indeed.py
tests/backend/scrapers/test_monster.py
tests/backend/tools/__init__.py
tests/backend/tools/test_delay.py
tests/backend/tools/test_filters.py
tests/backend/tools/test_tools.py
tests/config/__init__.py
tests/config/test_cli.py
tests/config/test_delay.py
tests/config/test_manager.py
tests/config/test_proxy.py
tests/config/test_search.py
JobFunnel-3.0.0.dist-info/LICENSE
JobFunnel-3.0.0.dist-info/METADATA
JobFunnel-3.0.0.dist-info/WHEEL
JobFunnel-3.0.0.dist-info/entry_points.txt
JobFunnel-3.0.0.dist-info/top_level.txt
JobFunnel-3.0.0.dist-info/RECORD
