Metadata-Version: 2.1
Name: JobFunnel
Version: 3.0.0
Summary: Automated tool for scraping job postings.
Home-page: https://github.com/PaulMcInnis/JobFunnel
Author: Paul McInnis, Bradley Kohler, Jose Alarcon, Erich Mengore, Mark van der Broek
Author-email: paulmcinnis99@gmail.com
License: MIT License
Platform: UNKNOWN
Classifier: License :: OSI Approved :: MIT License
Classifier: Programming Language :: Python :: 3
Classifier: Programming Language :: Python :: 3.8
Requires-Python: >=3.8.0
Requires-Dist: beautifulsoup4 (>=4.6.3)
Requires-Dist: lxml (>=4.2.4)
Requires-Dist: requests (>=2.19.1)
Requires-Dist: python-dateutil (>=2.8.0)
Requires-Dist: PyYAML (>=5.1)
Requires-Dist: scikit-learn (>=0.21.2)
Requires-Dist: nltk (>=3.4.1)
Requires-Dist: scipy (>=1.4.1)
Requires-Dist: pytest (>=5.3.1)
Requires-Dist: pytest-mock (>=3.1.1)
Requires-Dist: selenium (>=3.141.0)
Requires-Dist: webdriver-manager (>=2.4.0)
Requires-Dist: Cerberus (>=1.3.2)
Requires-Dist: tqdm (>=4.47.0)
